CHANGES.txt
LICENSE.txt
MANIFEST.in
README.txt
setup.py
Christofides/__init__.py
Christofides/christofides.py
Christofides/graph.py
Christofides.egg-info/PKG-INFO
Christofides.egg-info/SOURCES.txt
Christofides.egg-info/dependency_links.txt
Christofides.egg-info/requires.txt
Christofides.egg-info/top_level.txt
docs/Christofides.txt