Metadata-Version: 1.0
Name: Christofides
Version: 1.0.1
Summary: Christofides Algorithm for TSP.
Home-page: http://pypi.python.org/pypi/Christofides/
Author: Duvvuri Surya Rahul
Author-email: dsrahul@outlook.com
License: LICENSE.txt
Platform: UNKNOWN
